plumpy/__init__.py
plumpy/communications.py
plumpy/event_helper.py
plumpy/events.py
plumpy/exceptions.py
plumpy/futures.py
plumpy/lang.py
plumpy/loaders.py
plumpy/mixins.py
plumpy/persistence.py
plumpy/ports.py
plumpy/process_comms.py
plumpy/process_listener.py
plumpy/process_spec.py
plumpy/process_states.py
plumpy/processes.py
plumpy/py.typed
plumpy/settings.py
plumpy/utils.py
plumpy/workchains.py
plumpy/base/__init__.py
plumpy/base/state_machine.py
plumpy/base/utils.py
plumpy-0.25.1.dist-info/licenses/LICENSE.txt
plumpy-0.25.1.dist-info/WHEEL
plumpy-0.25.1.dist-info/METADATA
plumpy-0.25.1.dist-info/RECORD
